gino_aiohttp.py
gino_aiohttp-0.2.0.dist-info/entry_points.txt
gino_aiohttp-0.2.0.dist-info/LICENSE
gino_aiohttp-0.2.0.dist-info/WHEEL
gino_aiohttp-0.2.0.dist-info/METADATA
gino_aiohttp-0.2.0.dist-info/RECORD
