Metadata-Version: 2.1
Name: gino-aiohttp
Version: 0.2.0
Summary: An extension for GINO to integrate with aiohttp
Home-page: https://github.com/python-gino/gino-aiohttp
License: BSD-3-Clause
Keywords: sqlalchemy,python3,aiohttp,gino
Author: Fantix King
Author-email: fantix.king@gmail.com
Requires-Python: >=3.6,<4.0
Classifier: Development Status :: 4 - Beta
Classifier: Intended Audience :: Developers
Classifier: License :: OSI Approved :: BSD License
Classifier: Natural Language :: English
Classifier: Programming Language :: Python :: 3
Classifier: Programming Language :: Python :: 3.6
Classifier: Programming Language :: Python :: 3.7
Classifier: Programming Language :: Python :: 3.8
Classifier: Programming Language :: Python :: 3.9
Requires-Dist: aiohttp (>=3.7.2,<4.0.0)
Requires-Dist: gino (>=1.0.1,<2.0.0)
Project-URL: Documentation, https://python-gino.org/docs/
Project-URL: Repository, https://github.com/python-gino/gino-aiohttp
